convlstm_mlx/__init__.py
convlstm_mlx/conv_lstm.py
convlstm_mlx-0.1.1.dist-info/METADATA
convlstm_mlx-0.1.1.dist-info/WHEEL
convlstm_mlx-0.1.1.dist-info/top_level.txt
convlstm_mlx-0.1.1.dist-info/RECORD
