Metadata-Version: 2.1
Name: convlstm-mlx
Version: 0.1.1
Summary: An MLX implementation of ConvLSTM
Home-page: https://github.com/tomo-oga/convlstm-mlx
Author: Tomohiro Oga
Author-email: oga.t@northeastern.edu
License: MIT
Classifier: Programming Language :: Python :: 3
Classifier: License :: OSI Approved :: MIT License
Classifier: Development Status :: 3 - Alpha
Requires-Python: >=3.7
Requires-Dist: mlx
